canvas_tools/__init__.py
canvas_tools/canvas.py
canvas_pilot-0.1.3.dist-info/LICENSE
canvas_pilot-0.1.3.dist-info/METADATA
canvas_pilot-0.1.3.dist-info/WHEEL
canvas_pilot-0.1.3.dist-info/entry_points.txt
canvas_pilot-0.1.3.dist-info/top_level.txt
canvas_pilot-0.1.3.dist-info/RECORD
