Metadata-Version: 2.1
Name: canvas-pilot
Version: 0.1.3
Summary: A command-line tool for managing Canvas courses, fetching assignments, and grades.
Home-page: https://github.com/realzza/canvas-cli
Author: Ziang Zhou
Author-email: ziang.zhou518@gmail.com
License: GPLv3+
Keywords: canvas api cli
Classifier: Development Status :: 3 - Alpha
Classifier: Intended Audience :: Education
Classifier: License :: OSI Approved :: GNU General Public License v3 or later (GPLv3+)
Classifier: Programming Language :: Python :: 3
Classifier: Programming Language :: Python :: 3.6
Classifier: Programming Language :: Python :: 3.7
Classifier: Programming Language :: Python :: 3.8
Classifier: Programming Language :: Python :: 3.9
Requires-Python: >=3.6, <4
License-File: LICENSE
Requires-Dist: requests
Requires-Dist: icalendar
Requires-Dist: click
Requires-Dist: getpass4
